{
  "1554": {
    "ano_passado": "[{\"quantidade\":13297.0,\"sellout\":111999.570000001},{\"quantidade\":436.0,\"sellout\":3881.8}]",
    "ano_corrente": "[{\"quantidade\":13297.0,\"sellout\":111999.570000001},{\"quantidade\":436.0,\"sellout\":3881.8}]"
  },
  "1627": {
    "ano_passado": "[{\"quantidade\":5983.0,\"sellout\":64707.6499999999},{\"quantidade\":615.0,\"sellout\":6227.76}]",
    "ano_corrente": "[{\"quantidade\":5983.0,\"sellout\":64707.6499999999},{\"quantidade\":615.0,\"sellout\":6227.76}]"
  },
  "1651": {
    "ano_passado": "[{\"quantidade\":1749.0,\"sellout\":13617.82},{\"quantidade\":304.0,\"sellout\":2764.01}]",
    "ano_corrente": "[{\"quantidade\":1749.0,\"sellout\":13617.82},{\"quantidade\":304.0,\"sellout\":2764.01}]"
  },
  "1708": {
    "ano_passado": "[{\"quantidade\":15148.0,\"sellout\":161187.75},{\"quantidade\":1722.0,\"sellout\":19280.68}]",
    "ano_corrente": "[{\"quantidade\":15148.0,\"sellout\":161187.75},{\"quantidade\":1722.0,\"sellout\":19280.68}]"
  },
  "1759": {
    "ano_passado": "[{\"quantidade\":9257.0,\"sellout\":98741.2000000001},{\"quantidade\":806.0,\"sellout\":9420.83}]",
    "ano_corrente": "[{\"quantidade\":9257.0,\"sellout\":98741.2000000001},{\"quantidade\":806.0,\"sellout\":9420.83}]"
  },
  "2038": {
    "ano_passado": "[{\"quantidade\":14477.0,\"sellout\":166102.41},{\"quantidade\":1474.0,\"sellout\":16209.7}]",
    "ano_corrente": "[{\"quantidade\":14477.0,\"sellout\":166102.41},{\"quantidade\":1474.0,\"sellout\":16209.7}]"
  },
  "2062": {
    "ano_passado": "[{\"quantidade\":14113.0,\"sellout\":146265.460000001},{\"quantidade\":1243.0,\"sellout\":14021.99}]",
    "ano_corrente": "[{\"quantidade\":14113.0,\"sellout\":146265.460000001},{\"quantidade\":1243.0,\"sellout\":14021.99}]"
  },
  "2569": {
    "ano_passado": "[{\"quantidade\":6068.0,\"sellout\":68045.8799999999},{\"quantidade\":635.0,\"sellout\":6909.47}]",
    "ano_corrente": "[{\"quantidade\":6068.0,\"sellout\":68045.8799999999},{\"quantidade\":635.0,\"sellout\":6909.47}]"
  },
  "2968": {
    "ano_passado": "[{\"quantidade\":7982.0,\"sellout\":98676.2200000001},{\"quantidade\":751.0,\"sellout\":10042.84}]",
    "ano_corrente": "[{\"quantidade\":7982.0,\"sellout\":98676.2200000001},{\"quantidade\":751.0,\"sellout\":10042.84}]"
  },
  "3719": {
    "ano_passado": "[{\"quantidade\":12599.0,\"sellout\":141159.09},{\"quantidade\":1033.0,\"sellout\":12444.28}]",
    "ano_corrente": "[{\"quantidade\":12599.0,\"sellout\":141159.09},{\"quantidade\":1033.0,\"sellout\":12444.28}]"
  },
  "3824": {
    "ano_passado": "[{\"quantidade\":4608.0,\"sellout\":53704.3399999999},{\"quantidade\":636.0,\"sellout\":7432.86}]",
    "ano_corrente": "[{\"quantidade\":4608.0,\"sellout\":53704.3399999999},{\"quantidade\":636.0,\"sellout\":7432.86}]"
  },
  "3948": {
    "ano_passado": "[{\"quantidade\":9451.0,\"sellout\":113461.28},{\"quantidade\":1363.0,\"sellout\":23245.01}]",
    "ano_corrente": "[{\"quantidade\":9451.0,\"sellout\":113461.28},{\"quantidade\":1363.0,\"sellout\":23245.01}]"
  },
  "3972": {
    "ano_passado": "[{\"quantidade\":7643.0,\"sellout\":98908.47},{\"quantidade\":687.0,\"sellout\":8727.02}]",
    "ano_corrente": "[{\"quantidade\":7643.0,\"sellout\":98908.47},{\"quantidade\":687.0,\"sellout\":8727.02}]"
  },
  "4243": {
    "ano_passado": "[{\"quantidade\":11948.0,\"sellout\":141545.57},{\"quantidade\":1084.0,\"sellout\":12548.21}]",
    "ano_corrente": "[{\"quantidade\":11948.0,\"sellout\":141545.57},{\"quantidade\":1084.0,\"sellout\":12548.21}]"
  },
  "4251": {
    "ano_passado": "[{\"quantidade\":18604.0,\"sellout\":222294.32},{\"quantidade\":1683.0,\"sellout\":22062.2}]",
    "ano_corrente": "[{\"quantidade\":18604.0,\"sellout\":222294.32},{\"quantidade\":1683.0,\"sellout\":22062.2}]"
  },
  "4570": {
    "ano_passado": "[{\"quantidade\":11277.0,\"sellout\":118115.31},{\"quantidade\":1065.0,\"sellout\":12236.63}]",
    "ano_corrente": "[{\"quantidade\":11277.0,\"sellout\":118115.31},{\"quantidade\":1065.0,\"sellout\":12236.63}]"
  },
  "4901": {
    "ano_passado": "[{\"quantidade\":9773.0,\"sellout\":113280.28},{\"quantidade\":579.0,\"sellout\":8248.07}]",
    "ano_corrente": "[{\"quantidade\":9773.0,\"sellout\":113280.28},{\"quantidade\":579.0,\"sellout\":8248.07}]"
  },
  "4952": {
    "ano_passado": "[{\"quantidade\":6788.0,\"sellout\":71927.6699999996},{\"quantidade\":640.0,\"sellout\":7035.43}]",
    "ano_corrente": "[{\"quantidade\":6788.0,\"sellout\":71927.6699999996},{\"quantidade\":640.0,\"sellout\":7035.43}]"
  },
  "5100": {
    "ano_passado": "[{\"quantidade\":7639.0,\"sellout\":81634.9299999997},{\"quantidade\":853.0,\"sellout\":10922.55}]",
    "ano_corrente": "[{\"quantidade\":7639.0,\"sellout\":81634.9299999997},{\"quantidade\":853.0,\"sellout\":10922.55}]"
  },
  "5150": {
    "ano_passado": "[{\"quantidade\":8880.0,\"sellout\":111067.79},{\"quantidade\":957.0,\"sellout\":12439.27}]",
    "ano_corrente": "[{\"quantidade\":8880.0,\"sellout\":111067.79},{\"quantidade\":957.0,\"sellout\":12439.27}]"
  },
  "5266": {
    "ano_passado": "[{\"quantidade\":20232.0,\"sellout\":232645.761334829}]",
    "ano_corrente": "[{\"quantidade\":20232.0,\"sellout\":232645.761334829}]"
  },
  "5282": {
    "ano_passado": "[{\"quantidade\":7777.0,\"sellout\":83941.8099999998},{\"quantidade\":713.0,\"sellout\":8144.19}]",
    "ano_corrente": "[{\"quantidade\":7777.0,\"sellout\":83941.8099999998},{\"quantidade\":713.0,\"sellout\":8144.19}]"
  },
  "5320": {
    "ano_passado": "[{\"quantidade\":8205.0,\"sellout\":93835.15},{\"quantidade\":791.0,\"sellout\":11434.15}]",
    "ano_corrente": "[{\"quantidade\":8205.0,\"sellout\":93835.15},{\"quantidade\":791.0,\"sellout\":11434.15}]"
  },
  "5347": {
    "ano_passado": "[{\"quantidade\":13166.0,\"sellout\":135738.07},{\"quantidade\":1280.0,\"sellout\":16130.91}]",
    "ano_corrente": "[{\"quantidade\":13166.0,\"sellout\":135738.07},{\"quantidade\":1280.0,\"sellout\":16130.91}]"
  },
  "5355": {
    "ano_passado": "[{\"quantidade\":6496.0,\"sellout\":77540.6999999999},{\"quantidade\":750.0,\"sellout\":8945.96}]",
    "ano_corrente": "[{\"quantidade\":6496.0,\"sellout\":77540.6999999999},{\"quantidade\":750.0,\"sellout\":8945.96}]"
  },
  "5363": {
    "ano_passado": "[{\"quantidade\":10549.0,\"sellout\":128062.05},{\"quantidade\":1093.0,\"sellout\":13375.89}]",
    "ano_corrente": "[{\"quantidade\":10549.0,\"sellout\":128062.05},{\"quantidade\":1093.0,\"sellout\":13375.89}]"
  },
  "5622": {
    "ano_passado": "[{\"quantidade\":8614.0,\"sellout\":100943.33},{\"quantidade\":900.0,\"sellout\":11875.08}]",
    "ano_corrente": "[{\"quantidade\":8614.0,\"sellout\":100943.33},{\"quantidade\":900.0,\"sellout\":11875.08}]"
  },
  "5720": {
    "ano_passado": "[{\"quantidade\":17343.0,\"sellout\":198654.86},{\"quantidade\":1759.0,\"sellout\":21928.69}]",
    "ano_corrente": "[{\"quantidade\":17343.0,\"sellout\":198654.86},{\"quantidade\":1759.0,\"sellout\":21928.69}]"
  },
  "5878": {
    "ano_passado": "[{\"quantidade\":30209.0,\"sellout\":355190.137096741}]",
    "ano_corrente": "[{\"quantidade\":30209.0,\"sellout\":355190.137096741}]"
  },
  "6149": {
    "ano_passado": "[{\"quantidade\":7787.0,\"sellout\":91176.5899999996},{\"quantidade\":751.0,\"sellout\":9275.6}]",
    "ano_corrente": "[{\"quantidade\":7787.0,\"sellout\":91176.5899999996},{\"quantidade\":751.0,\"sellout\":9275.6}]"
  },
  "6335": {
    "ano_passado": "[{\"quantidade\":11824.0,\"sellout\":113010.710767827},{\"quantidade\":925.0,\"sellout\":10513.49}]",
    "ano_corrente": "[{\"quantidade\":11824.0,\"sellout\":113010.710767827},{\"quantidade\":925.0,\"sellout\":10513.49}]"
  },
  "7080": {
    "ano_passado": "[{\"quantidade\":12332.0,\"sellout\":137596.47},{\"quantidade\":1238.0,\"sellout\":12927.69}]",
    "ano_corrente": "[{\"quantidade\":12332.0,\"sellout\":137596.47},{\"quantidade\":1238.0,\"sellout\":12927.69}]"
  },
  "7099": {
    "ano_passado": "[{\"quantidade\":1185.0,\"sellout\":13536.07}]",
    "ano_corrente": "[{\"quantidade\":1185.0,\"sellout\":13536.07}]"
  },
  "7170": {
    "ano_passado": "[{\"quantidade\":7086.0,\"sellout\":12397.75}]",
    "ano_corrente": "[{\"quantidade\":7086.0,\"sellout\":12397.75}]"
  },
  "7714": {
    "ano_passado": "[{\"quantidade\":6281.0,\"sellout\":69858.1700000001},{\"quantidade\":652.0,\"sellout\":8976.33}]",
    "ano_corrente": "[{\"quantidade\":6281.0,\"sellout\":69858.1700000001},{\"quantidade\":652.0,\"sellout\":8976.33}]"
  },
  "7943": {
    "ano_passado": "[{\"quantidade\":12204.0,\"sellout\":127056.73},{\"quantidade\":1089.0,\"sellout\":11515.64}]",
    "ano_corrente": "[{\"quantidade\":12204.0,\"sellout\":127056.73},{\"quantidade\":1089.0,\"sellout\":11515.64}]"
  },
  "8109": {
    "ano_passado": "[{\"quantidade\":34489.0,\"sellout\":397064.719999996},{\"quantidade\":2519.0,\"sellout\":31616.9300000001}]",
    "ano_corrente": "[{\"quantidade\":34489.0,\"sellout\":397064.719999996},{\"quantidade\":2519.0,\"sellout\":31616.9300000001}]"
  },
  "8354": {
    "ano_passado": "[{\"quantidade\":6774.0,\"sellout\":78918.7000000001},{\"quantidade\":701.0,\"sellout\":11502.2}]",
    "ano_corrente": "[{\"quantidade\":6774.0,\"sellout\":78918.7000000001},{\"quantidade\":701.0,\"sellout\":11502.2}]"
  },
  "8800": {
    "ano_passado": "[{\"quantidade\":5280.0,\"sellout\":57507.3499999999},{\"quantidade\":592.0,\"sellout\":7510.91}]",
    "ano_corrente": "[{\"quantidade\":5280.0,\"sellout\":57507.3499999999},{\"quantidade\":592.0,\"sellout\":7510.91}]"
  },
  "8850": {
    "ano_passado": "[{\"quantidade\":6479.0,\"sellout\":69118.39}]",
    "ano_corrente": "[{\"quantidade\":6479.0,\"sellout\":69118.39}]"
  },
  "8990": {
    "ano_passado": "[{\"quantidade\":9319.0,\"sellout\":93981.2000000002},{\"quantidade\":832.0,\"sellout\":8427.67}]",
    "ano_corrente": "[{\"quantidade\":9319.0,\"sellout\":93981.2000000002},{\"quantidade\":832.0,\"sellout\":8427.67}]"
  },
  "9300": {
    "ano_passado": "[{\"quantidade\":6638.0,\"sellout\":77370.1599999995},{\"quantidade\":586.0,\"sellout\":5942.82}]",
    "ano_corrente": "[{\"quantidade\":6638.0,\"sellout\":77370.1599999995},{\"quantidade\":586.0,\"sellout\":5942.82}]"
  },
  "9539": {
    "ano_passado": "[{\"quantidade\":15251.0,\"sellout\":175073.18},{\"quantidade\":1577.0,\"sellout\":18144.78}]",
    "ano_corrente": "[{\"quantidade\":15251.0,\"sellout\":175073.18},{\"quantidade\":1577.0,\"sellout\":18144.78}]"
  },
  "10162": {
    "ano_passado": "[{\"quantidade\":9928.0,\"sellout\":104923.74},{\"quantidade\":1194.0,\"sellout\":14250.0}]",
    "ano_corrente": "[{\"quantidade\":9928.0,\"sellout\":104923.74},{\"quantidade\":1194.0,\"sellout\":14250.0}]"
  },
  "10413": {
    "ano_passado": "[{\"quantidade\":6191.0,\"sellout\":75651.8},{\"quantidade\":634.0,\"sellout\":8155.33}]",
    "ano_corrente": "[{\"quantidade\":6191.0,\"sellout\":75651.8},{\"quantidade\":634.0,\"sellout\":8155.33}]"
  },
  "10456": {
    "ano_passado": "[{\"quantidade\":10442.0,\"sellout\":114088.78},{\"quantidade\":1136.0,\"sellout\":13574.59}]",
    "ano_corrente": "[{\"quantidade\":10442.0,\"sellout\":114088.78},{\"quantidade\":1136.0,\"sellout\":13574.59}]"
  },
  "11525": {
    "ano_passado": "[{\"quantidade\":20872.0,\"sellout\":229719.19},{\"quantidade\":1778.0,\"sellout\":19893.45}]",
    "ano_corrente": "[{\"quantidade\":20872.0,\"sellout\":229719.19},{\"quantidade\":1778.0,\"sellout\":19893.45}]"
  },
  "11827": {
    "ano_passado": "[{\"quantidade\":13710.0,\"sellout\":158601.06},{\"quantidade\":1743.0,\"sellout\":22357.41}]",
    "ano_corrente": "[{\"quantidade\":13710.0,\"sellout\":158601.06},{\"quantidade\":1743.0,\"sellout\":22357.41}]"
  },
  "11967": {
    "ano_passado": "[{\"quantidade\":5181.0,\"sellout\":62230.9099999998},{\"quantidade\":469.0,\"sellout\":5950.13}]",
    "ano_corrente": "[{\"quantidade\":5181.0,\"sellout\":62230.9099999998},{\"quantidade\":469.0,\"sellout\":5950.13}]"
  },
  "12041": {
    "ano_passado": "[{\"quantidade\":5279.0,\"sellout\":59780.7500000001},{\"quantidade\":461.0,\"sellout\":4772.42}]",
    "ano_corrente": "[{\"quantidade\":5279.0,\"sellout\":59780.7500000001},{\"quantidade\":461.0,\"sellout\":4772.42}]"
  },
  "12130": {
    "ano_passado": "[{\"quantidade\":4026.0,\"sellout\":49269.2600000001},{\"quantidade\":421.0,\"sellout\":5097.56}]",
    "ano_corrente": "[{\"quantidade\":4026.0,\"sellout\":49269.2600000001},{\"quantidade\":421.0,\"sellout\":5097.56}]"
  },
  "13226": {
    "ano_passado": "[{\"quantidade\":11616.0,\"sellout\":131151.63},{\"quantidade\":1419.0,\"sellout\":17779.38}]",
    "ano_corrente": "[{\"quantidade\":11616.0,\"sellout\":131151.63},{\"quantidade\":1419.0,\"sellout\":17779.38}]"
  },
  "13234": {
    "ano_passado": "[{\"quantidade\":14929.0,\"sellout\":156842.66},{\"quantidade\":1329.0,\"sellout\":13113.25}]",
    "ano_corrente": "[{\"quantidade\":14929.0,\"sellout\":156842.66},{\"quantidade\":1329.0,\"sellout\":13113.25}]"
  },
  "13650": {
    "ano_passado": "[{\"quantidade\":3996.0,\"sellout\":40175.84},{\"quantidade\":442.0,\"sellout\":4918.36}]",
    "ano_corrente": "[{\"quantidade\":3996.0,\"sellout\":40175.84},{\"quantidade\":442.0,\"sellout\":4918.36}]"
  },
  "14087": {
    "ano_passado": "[{\"quantidade\":11810.0,\"sellout\":133230.59},{\"quantidade\":1088.0,\"sellout\":12947.71}]",
    "ano_corrente": "[{\"quantidade\":11810.0,\"sellout\":133230.59},{\"quantidade\":1088.0,\"sellout\":12947.71}]"
  },
  "15121": {
    "ano_passado": "[{\"quantidade\":8696.0,\"sellout\":96483.5300000002},{\"quantidade\":1039.0,\"sellout\":12155.81}]",
    "ano_corrente": "[{\"quantidade\":8696.0,\"sellout\":96483.5300000002},{\"quantidade\":1039.0,\"sellout\":12155.81}]"
  },
  "15245": {
    "ano_passado": "[{\"quantidade\":4128.0,\"sellout\":49154.0200000001},{\"quantidade\":406.0,\"sellout\":4557.15}]",
    "ano_corrente": "[{\"quantidade\":4128.0,\"sellout\":49154.0200000001},{\"quantidade\":406.0,\"sellout\":4557.15}]"
  },
  "15385": {
    "ano_passado": "[{\"quantidade\":7357.0,\"sellout\":83012.1999999999},{\"quantidade\":817.0,\"sellout\":9709.29}]",
    "ano_corrente": "[{\"quantidade\":7357.0,\"sellout\":83012.1999999999},{\"quantidade\":817.0,\"sellout\":9709.29}]"
  },
  "16497": {
    "ano_passado": "[{\"quantidade\":5651.0,\"sellout\":66323.5699999999},{\"quantidade\":421.0,\"sellout\":5880.01}]",
    "ano_corrente": "[{\"quantidade\":5651.0,\"sellout\":66323.5699999999},{\"quantidade\":421.0,\"sellout\":5880.01}]"
  },
  "16624": {
    "ano_passado": "[{\"quantidade\":18724.0,\"sellout\":221104.9},{\"quantidade\":1696.0,\"sellout\":21221.08}]",
    "ano_corrente": "[{\"quantidade\":18724.0,\"sellout\":221104.9},{\"quantidade\":1696.0,\"sellout\":21221.08}]"
  },
  "16632": {
    "ano_passado": "[{\"quantidade\":17689.0,\"sellout\":190434.06},{\"quantidade\":1912.0,\"sellout\":21808.24}]",
    "ano_corrente": "[{\"quantidade\":17689.0,\"sellout\":190434.06},{\"quantidade\":1912.0,\"sellout\":21808.24}]"
  },
  "16675": {
    "ano_passado": "[{\"quantidade\":4758.0,\"sellout\":41596.51},{\"quantidade\":433.0,\"sellout\":4145.61}]",
    "ano_corrente": "[{\"quantidade\":4758.0,\"sellout\":41596.51},{\"quantidade\":433.0,\"sellout\":4145.61}]"
  },
  "16780": {
    "ano_passado": "[{\"quantidade\":91.0,\"sellout\":622.8301470517}]",
    "ano_corrente": "[{\"quantidade\":91.0,\"sellout\":622.8301470517}]"
  },
  "16829": {
    "ano_passado": "[{\"quantidade\":9826.0,\"sellout\":110735.54},{\"quantidade\":977.0,\"sellout\":11715.52}]",
    "ano_corrente": "[{\"quantidade\":9826.0,\"sellout\":110735.54},{\"quantidade\":977.0,\"sellout\":11715.52}]"
  },
  "17132": {
    "ano_passado": "[{\"quantidade\":14679.0,\"sellout\":147359.2},{\"quantidade\":1532.0,\"sellout\":18771.67}]",
    "ano_corrente": "[{\"quantidade\":14679.0,\"sellout\":147359.2},{\"quantidade\":1532.0,\"sellout\":18771.67}]"
  },
  "18066": {
    "ano_passado": "[{\"quantidade\":6220.0,\"sellout\":70300.62},{\"quantidade\":532.0,\"sellout\":6280.55}]",
    "ano_corrente": "[{\"quantidade\":6220.0,\"sellout\":70300.62},{\"quantidade\":532.0,\"sellout\":6280.55}]"
  },
  "19143": {
    "ano_passado": "[{\"quantidade\":12686.0,\"sellout\":135084.66},{\"quantidade\":1482.0,\"sellout\":15406.66}]",
    "ano_corrente": "[{\"quantidade\":12686.0,\"sellout\":135084.66},{\"quantidade\":1482.0,\"sellout\":15406.66}]"
  },
  "19348": {
    "ano_passado": "[{\"quantidade\":4431.0,\"sellout\":89099.4299999994},{\"quantidade\":906.0,\"sellout\":17087.03}]",
    "ano_corrente": "[{\"quantidade\":4431.0,\"sellout\":89099.4299999994},{\"quantidade\":906.0,\"sellout\":17087.03}]"
  },
  "19615": {
    "ano_passado": "[{\"quantidade\":9729.0,\"sellout\":103503.01},{\"quantidade\":1053.0,\"sellout\":12052.63}]",
    "ano_corrente": "[{\"quantidade\":9729.0,\"sellout\":103503.01},{\"quantidade\":1053.0,\"sellout\":12052.63}]"
  },
  "19844": {
    "ano_passado": "[{\"quantidade\":5154.0,\"sellout\":64682.8732180744}]",
    "ano_corrente": "[{\"quantidade\":5154.0,\"sellout\":64682.8732180744}]"
  },
  "20630": {
    "ano_passado": "[{\"quantidade\":7926.0,\"sellout\":90131.7099999993},{\"quantidade\":735.0,\"sellout\":9472.29}]",
    "ano_corrente": "[{\"quantidade\":7926.0,\"sellout\":90131.7099999993},{\"quantidade\":735.0,\"sellout\":9472.29}]"
  },
  "21083": {
    "ano_passado": "[{\"quantidade\":13651.0,\"sellout\":152520.2},{\"quantidade\":1328.0,\"sellout\":16434.31}]",
    "ano_corrente": "[{\"quantidade\":13651.0,\"sellout\":152520.2},{\"quantidade\":1328.0,\"sellout\":16434.31}]"
  },
  "21393": {
    "ano_passado": "[{\"quantidade\":12933.0,\"sellout\":146802.09},{\"quantidade\":1745.0,\"sellout\":19528.24}]",
    "ano_corrente": "[{\"quantidade\":12933.0,\"sellout\":146802.09},{\"quantidade\":1745.0,\"sellout\":19528.24}]"
  },
  "22152": {
    "ano_passado": "[{\"quantidade\":5967.0,\"sellout\":69413.3099999998},{\"quantidade\":710.0,\"sellout\":8370.31}]",
    "ano_corrente": "[{\"quantidade\":5967.0,\"sellout\":69413.3099999998},{\"quantidade\":710.0,\"sellout\":8370.31}]"
  },
  "22322": {
    "ano_passado": "[{\"quantidade\":6311.0,\"sellout\":63221.9199999999},{\"quantidade\":763.0,\"sellout\":7715.58}]",
    "ano_corrente": "[{\"quantidade\":6311.0,\"sellout\":63221.9199999999},{\"quantidade\":763.0,\"sellout\":7715.58}]"
  },
  "22470": {
    "ano_passado": "[{\"quantidade\":11616.0,\"sellout\":124161.49},{\"quantidade\":916.0,\"sellout\":9566.48}]",
    "ano_corrente": "[{\"quantidade\":11616.0,\"sellout\":124161.49},{\"quantidade\":916.0,\"sellout\":9566.48}]"
  },
  "22616": {
    "ano_passado": "[{\"quantidade\":14188.0,\"sellout\":152407.530000001},{\"quantidade\":1134.0,\"sellout\":12362.83}]",
    "ano_corrente": "[{\"quantidade\":14188.0,\"sellout\":152407.530000001},{\"quantidade\":1134.0,\"sellout\":12362.83}]"
  },
  "22675": {
    "ano_passado": "[{\"quantidade\":5152.0,\"sellout\":59041.06},{\"quantidade\":695.0,\"sellout\":9672.07}]",
    "ano_corrente": "[{\"quantidade\":5152.0,\"sellout\":59041.06},{\"quantidade\":695.0,\"sellout\":9672.07}]"
  },
  "22896": {
    "ano_passado": "[{\"quantidade\":11038.0,\"sellout\":111260.259999999},{\"quantidade\":1096.0,\"sellout\":11178.17}]",
    "ano_corrente": "[{\"quantidade\":11038.0,\"sellout\":111260.259999999},{\"quantidade\":1096.0,\"sellout\":11178.17}]"
  },
  "23647": {
    "ano_passado": "[{\"quantidade\":7248.0,\"sellout\":90613.98017196}]",
    "ano_corrente": "[{\"quantidade\":7248.0,\"sellout\":90613.98017196}]"
  },
  "23710": {
    "ano_passado": "[{\"quantidade\":18383.0,\"sellout\":221348.083119795}]",
    "ano_corrente": "[{\"quantidade\":18383.0,\"sellout\":221348.083119795}]"
  },
  "23825": {
    "ano_passado": "[{\"quantidade\":10733.0,\"sellout\":122735.92},{\"quantidade\":1221.0,\"sellout\":14343.09}]",
    "ano_corrente": "[{\"quantidade\":10733.0,\"sellout\":122735.92},{\"quantidade\":1221.0,\"sellout\":14343.09}]"
  },
  "23884": {
    "ano_passado": "[{\"quantidade\":14449.0,\"sellout\":155618.17},{\"quantidade\":1499.0,\"sellout\":15433.62}]",
    "ano_corrente": "[{\"quantidade\":14449.0,\"sellout\":155618.17},{\"quantidade\":1499.0,\"sellout\":15433.62}]"
  },
  "24104": {
    "ano_passado": "[{\"quantidade\":9757.0,\"sellout\":117660.67},{\"quantidade\":909.0,\"sellout\":11133.6}]",
    "ano_corrente": "[{\"quantidade\":9757.0,\"sellout\":117660.67},{\"quantidade\":909.0,\"sellout\":11133.6}]"
  },
  "24414": {
    "ano_passado": "[{\"quantidade\":6553.0,\"sellout\":79346.0599999999},{\"quantidade\":674.0,\"sellout\":8513.66}]",
    "ano_corrente": "[{\"quantidade\":6553.0,\"sellout\":79346.0599999999},{\"quantidade\":674.0,\"sellout\":8513.66}]"
  },
  "24422": {
    "ano_passado": "[{\"quantidade\":31071.0,\"sellout\":341381.050000002},{\"quantidade\":2687.0,\"sellout\":29582.48}]",
    "ano_corrente": "[{\"quantidade\":31071.0,\"sellout\":341381.050000002},{\"quantidade\":2687.0,\"sellout\":29582.48}]"
  },
  "24430": {
    "ano_passado": "[{\"quantidade\":15859.0,\"sellout\":186451.43},{\"quantidade\":1588.0,\"sellout\":18977.82}]",
    "ano_corrente": "[{\"quantidade\":15859.0,\"sellout\":186451.43},{\"quantidade\":1588.0,\"sellout\":18977.82}]"
  },
  "24813": {
    "ano_passado": "[{\"quantidade\":4128.0,\"sellout\":46542.7000000001},{\"quantidade\":499.0,\"sellout\":5265.02}]",
    "ano_corrente": "[{\"quantidade\":4128.0,\"sellout\":46542.7000000001},{\"quantidade\":499.0,\"sellout\":5265.02}]"
  },
  "24821": {
    "ano_passado": "[{\"quantidade\":7251.0,\"sellout\":86107.2500000002},{\"quantidade\":739.0,\"sellout\":9119.22}]",
    "ano_corrente": "[{\"quantidade\":7251.0,\"sellout\":86107.2500000002},{\"quantidade\":739.0,\"sellout\":9119.22}]"
  },
  "25526": {
    "ano_passado": "[{\"quantidade\":9586.0,\"sellout\":101272.01},{\"quantidade\":1009.0,\"sellout\":12943.27}]",
    "ano_corrente": "[{\"quantidade\":9586.0,\"sellout\":101272.01},{\"quantidade\":1009.0,\"sellout\":12943.27}]"
  },
  "25631": {
    "ano_passado": "[{\"quantidade\":10661.0,\"sellout\":133794.64},{\"quantidade\":1127.0,\"sellout\":13864.5}]",
    "ano_corrente": "[{\"quantidade\":10661.0,\"sellout\":133794.64},{\"quantidade\":1127.0,\"sellout\":13864.5}]"
  },
  "25747": {
    "ano_passado": "[{\"quantidade\":10699.0,\"sellout\":122836.46},{\"quantidade\":898.0,\"sellout\":11049.11}]",
    "ano_corrente": "[{\"quantidade\":10699.0,\"sellout\":122836.46},{\"quantidade\":898.0,\"sellout\":11049.11}]"
  },
  "26026": {
    "ano_passado": "[{\"quantidade\":8518.0,\"sellout\":96274.6399999999},{\"quantidade\":1852.0,\"sellout\":15230.0}]",
    "ano_corrente": "[{\"quantidade\":8518.0,\"sellout\":96274.6399999999},{\"quantidade\":1852.0,\"sellout\":15230.0}]"
  },
  "26662": {
    "ano_passado": "[{\"quantidade\":7189.0,\"sellout\":91055.9100000003},{\"quantidade\":923.0,\"sellout\":10886.73}]",
    "ano_corrente": "[{\"quantidade\":7189.0,\"sellout\":91055.9100000003},{\"quantidade\":923.0,\"sellout\":10886.73}]"
  },
  "26670": {
    "ano_passado": "[{\"quantidade\":17963.0,\"sellout\":211930.940000002},{\"quantidade\":1762.0,\"sellout\":19884.54}]",
    "ano_corrente": "[{\"quantidade\":17963.0,\"sellout\":211930.940000002},{\"quantidade\":1762.0,\"sellout\":19884.54}]"
  },
  "26778": {
    "ano_passado": "[{\"quantidade\":3226.0,\"sellout\":35270.39},{\"quantidade\":375.0,\"sellout\":3877.52}]",
    "ano_corrente": "[{\"quantidade\":3226.0,\"sellout\":35270.39},{\"quantidade\":375.0,\"sellout\":3877.52}]"
  },
  "26824": {
    "ano_passado": "[{\"quantidade\":9269.0,\"sellout\":105993.43},{\"quantidade\":886.0,\"sellout\":10614.78}]",
    "ano_corrente": "[{\"quantidade\":9269.0,\"sellout\":105993.43},{\"quantidade\":886.0,\"sellout\":10614.78}]"
  },
  "26999": {
    "ano_passado": "[{\"quantidade\":7529.0,\"sellout\":83724.6700000001},{\"quantidade\":779.0,\"sellout\":9106.28}]",
    "ano_corrente": "[{\"quantidade\":7529.0,\"sellout\":83724.6700000001},{\"quantidade\":779.0,\"sellout\":9106.28}]"
  },
  "27006": {
    "ano_passado": "[{\"quantidade\":11259.0,\"sellout\":121098.3},{\"quantidade\":986.0,\"sellout\":12443.17}]",
    "ano_corrente": "[{\"quantidade\":11259.0,\"sellout\":121098.3},{\"quantidade\":986.0,\"sellout\":12443.17}]"
  },
  "27073": {
    "ano_passado": "[{\"quantidade\":16510.0,\"sellout\":182117.290000001},{\"quantidade\":1671.0,\"sellout\":22302.18}]",
    "ano_corrente": "[{\"quantidade\":16510.0,\"sellout\":182117.290000001},{\"quantidade\":1671.0,\"sellout\":22302.18}]"
  },
  "27111": {
    "ano_passado": "[{\"quantidade\":7410.0,\"sellout\":85027.5600000001},{\"quantidade\":733.0,\"sellout\":8611.53}]",
    "ano_corrente": "[{\"quantidade\":7410.0,\"sellout\":85027.5600000001},{\"quantidade\":733.0,\"sellout\":8611.53}]"
  },
  "27170": {
    "ano_passado": "[{\"quantidade\":7286.0,\"sellout\":85689.0100000001},{\"quantidade\":619.0,\"sellout\":7938.47}]",
    "ano_corrente": "[{\"quantidade\":7286.0,\"sellout\":85689.0100000001},{\"quantidade\":619.0,\"sellout\":7938.47}]"
  },
  "27219": {
    "ano_passado": "[{\"quantidade\":14224.0,\"sellout\":162950.33},{\"quantidade\":1605.0,\"sellout\":19719.77}]",
    "ano_corrente": "[{\"quantidade\":14224.0,\"sellout\":162950.33},{\"quantidade\":1605.0,\"sellout\":19719.77}]"
  },
  "27480": {
    "ano_passado": "[{\"quantidade\":3895.0,\"sellout\":47759.94},{\"quantidade\":368.0,\"sellout\":4630.39}]",
    "ano_corrente": "[{\"quantidade\":3895.0,\"sellout\":47759.94},{\"quantidade\":368.0,\"sellout\":4630.39}]"
  },
  "33901": {
    "ano_passado": "[{\"quantidade\":14551.0,\"sellout\":153377.09},{\"quantidade\":1237.0,\"sellout\":13776.84}]",
    "ano_corrente": "[{\"quantidade\":14551.0,\"sellout\":153377.09},{\"quantidade\":1237.0,\"sellout\":13776.84}]"
  },
  "34100": {
    "ano_passado": "[{\"quantidade\":15413.0,\"sellout\":170541.979999999},{\"quantidade\":1240.0,\"sellout\":15069.51}]",
    "ano_corrente": "[{\"quantidade\":15413.0,\"sellout\":170541.979999999},{\"quantidade\":1240.0,\"sellout\":15069.51}]"
  },
  "34118": {
    "ano_passado": "[{\"quantidade\":2252.0,\"sellout\":26422.34},{\"quantidade\":217.0,\"sellout\":2366.46}]",
    "ano_corrente": "[{\"quantidade\":2252.0,\"sellout\":26422.34},{\"quantidade\":217.0,\"sellout\":2366.46}]"
  },
  "34134": {
    "ano_passado": "[{\"quantidade\":5280.0,\"sellout\":60406.0599999999},{\"quantidade\":729.0,\"sellout\":8087.81}]",
    "ano_corrente": "[{\"quantidade\":5280.0,\"sellout\":60406.0599999999},{\"quantidade\":729.0,\"sellout\":8087.81}]"
  },
  "34150": {
    "ano_passado": "[{\"quantidade\":13288.0,\"sellout\":150740.36},{\"quantidade\":1375.0,\"sellout\":15626.39}]",
    "ano_corrente": "[{\"quantidade\":13288.0,\"sellout\":150740.36},{\"quantidade\":1375.0,\"sellout\":15626.39}]"
  },
  "34860": {
    "ano_passado": "[{\"quantidade\":345.0,\"sellout\":4505.6240594322},{\"quantidade\":612.0,\"sellout\":7295.2996551222}]",
    "ano_corrente": "[{\"quantidade\":345.0,\"sellout\":4505.6240594322},{\"quantidade\":612.0,\"sellout\":7295.2996551222}]"
  },
  "34916": {
    "ano_passado": "[{\"quantidade\":5723.0,\"sellout\":61415.5737065728}]",
    "ano_corrente": "[{\"quantidade\":5723.0,\"sellout\":61415.5737065728}]"
  },
  "35254": {
    "ano_passado": "[{\"quantidade\":9147.0,\"sellout\":109956.17},{\"quantidade\":732.0,\"sellout\":9626.5}]",
    "ano_corrente": "[{\"quantidade\":9147.0,\"sellout\":109956.17},{\"quantidade\":732.0,\"sellout\":9626.5}]"
  },
  "35491": {
    "ano_passado": "[{\"quantidade\":1468.0,\"sellout\":16164.43},{\"quantidade\":104.0,\"sellout\":1003.8}]",
    "ano_corrente": "[{\"quantidade\":1468.0,\"sellout\":16164.43},{\"quantidade\":104.0,\"sellout\":1003.8}]"
  },
  "35785": {
    "ano_passado": "[{\"quantidade\":3194.0,\"sellout\":39391.77},{\"quantidade\":604.0,\"sellout\":7413.5}]",
    "ano_corrente": "[{\"quantidade\":3194.0,\"sellout\":39391.77},{\"quantidade\":604.0,\"sellout\":7413.5}]"
  },
  "35858": {
    "ano_passado": "[{\"quantidade\":5484.0,\"sellout\":60265.76},{\"quantidade\":512.0,\"sellout\":5573.77}]",
    "ano_corrente": "[{\"quantidade\":5484.0,\"sellout\":60265.76},{\"quantidade\":512.0,\"sellout\":5573.77}]"
  }
}