[
  {
    "data": "20200725",
    "lab": "Alfasigma Portugal",
    "0": [
      {
        "sellin": 7201.3684991538,
        "sellout_esse_ano": 373216.509570088,
        "sellout": 719780.747594568
      }
    ]
  },
  {
    "data": "20200725",
    "lab": "Bial",
    "0": [
      {
        "sellin": 13194.6690596131,
        "sellout_esse_ano": 1964935.22282164,
        "sellout": 3632563.61478922
      }
    ]
  },
  {
    "data": "20200725",
    "lab": "Biocodex",
    "0": [
      {
        "sellin": 1250.271,
        "sellout_esse_ano": 92320.0384039695,
        "sellout": 201665.422920771
      }
    ]
  },
  {
    "data": "20200725",
    "lab": "Biowell Europe Lda",
    "0": [
      {
        "sellin": 8416.6607194962,
        "sellout_esse_ano": 31939.7020000001,
        "sellout": 43586.0808927481
      }
    ]
  },
  {
    "data": "20200725",
    "lab": "Cuidafarma Lda",
    "0": [
      {
        "sellin": 0.0,
        "sellout_esse_ano": 64102.7500000001,
        "sellout": 71063.56
      }
    ]
  },
  {
    "data": "20200725",
    "lab": "Ferraz Lynce",
    "0": [
      {
        "sellin": 6257.2102527195,
        "sellout_esse_ano": 149335.633345281,
        "sellout": 272256.721125495
      }
    ]
  },
  {
    "data": "20200725",
    "lab": "GSK Consumer Healthcare",
    "0": [
      {
        "sellin": 182274.7187877704,
        "sellout_esse_ano": 1568691.52745899,
        "sellout": 2636586.70169634
      }
    ]
  },
  {
    "data": "20200725",
    "lab": "Generis",
    "0": [
      {
        "sellin": 0.0,
        "sellout_esse_ano": 2961367.42244937,
        "sellout": 5258665.23707339
      }
    ]
  },
  {
    "data": "20200725",
    "lab": "GlaxoSmithKline",
    "0": [
      {
        "sellin": 34342.3319738615,
        "sellout_esse_ano": 1999022.56894608,
        "sellout": 3763269.05214826
      }
    ]
  },
  {
    "data": "20200725",
    "lab": "Grupo Italfarmaco",
    "0": [
      {
        "sellin": 25221.9201229823,
        "sellout_esse_ano": 616346.968763291,
        "sellout": 1242152.1743908
      }
    ]
  },
  {
    "data": "20200725",
    "lab": "Jaba Recordati",
    "0": [
      {
        "sellin": 35712.2876832871,
        "sellout_esse_ano": 1113365.8499768,
        "sellout": 2118281.97473467
      }
    ]
  },
  {
    "data": "20200725",
    "lab": "Korangi",
    "0": [
      {
        "sellin": 6089.1253820939,
        "sellout_esse_ano": 74452.9631785137,
        "sellout": 156788.103982236
      }
    ]
  },
  {
    "data": "20200725",
    "lab": "Krka",
    "0": [
      {
        "sellin": 0.0,
        "sellout_esse_ano": 628890.139091394,
        "sellout": 1112630.23047444
      }
    ]
  },
  {
    "data": "20200725",
    "lab": "Laboratórios Atral",
    "0": [
      {
        "sellin": 18185.6115394732,
        "sellout_esse_ano": 617001.270158529,
        "sellout": 1221964.14492096
      }
    ]
  },
  {
    "data": "20200725",
    "lab": "MSD",
    "0": [
      {
        "sellin": 0.0,
        "sellout_esse_ano": 2740547.29635896,
        "sellout": 5173689.26236533
      }
    ]
  },
  {
    "data": "20200725",
    "lab": "Medinfar",
    "0": [
      {
        "sellin": 35686.2777907127,
        "sellout_esse_ano": 917951.55401125,
        "sellout": 1717996.32733428
      }
    ]
  },
  {
    "data": "20200725",
    "lab": "Menarini",
    "0": [
      {
        "sellin": 3145.9265670896,
        "sellout_esse_ano": 986405.381760164,
        "sellout": 1742561.59402176
      }
    ]
  },
  {
    "data": "20200725",
    "lab": "Mylan",
    "0": [
      {
        "sellin": 155403.4816666667,
        "sellout_esse_ano": 3196971.63016343,
        "sellout": 5998802.90549243
      }
    ]
  },
  {
    "data": "20200725",
    "lab": "Perrigo",
    "0": [
      {
        "sellin": 87068.8552901947,
        "sellout_esse_ano": 773679.564201436,
        "sellout": 1373545.51507285
      }
    ]
  },
  {
    "data": "20200725",
    "lab": "Pfizer",
    "0": [
      {
        "sellin": 36035.5074068802,
        "sellout_esse_ano": 1231418.3100915,
        "sellout": 2403048.68920474
      }
    ]
  },
  {
    "data": "20200725",
    "lab": "Pfizer Consumer Healthcare",
    "0": [
      {
        "sellin": 7239.1,
        "sellout_esse_ano": 211807.584613961,
        "sellout": 337684.915148356
      }
    ]
  },
  {
    "data": "20200725",
    "lab": "Phytoderm",
    "0": [
      {
        "sellin": 17016.8825902345,
        "sellout_esse_ano": 154972.717943957,
        "sellout": 338060.744938903
      }
    ]
  },
  {
    "data": "20200725",
    "lab": "Pierre Fabre Dermo-Cosmétique",
    "0": [
      {
        "sellin": 23524.8662645536,
        "sellout_esse_ano": 1238529.07490045,
        "sellout": 2063470.32468797
      }
    ]
  },
  {
    "data": "20200725",
    "lab": "Pierre Fabre Médicament",
    "0": [
      {
        "sellin": 0.0,
        "sellout_esse_ano": 292503.112403409,
        "sellout": 536226.504825141
      }
    ]
  },
  {
    "data": "20200725",
    "lab": "Procter & Gamble Health",
    "0": [
      {
        "sellin": 37388.2847058824,
        "sellout_esse_ano": 609651.47131447,
        "sellout": 1133922.17241266
      }
    ]
  },
  {
    "data": "20200725",
    "lab": "Reckitt Benckiser",
    "0": [
      {
        "sellin": 68868.3993623272,
        "sellout_esse_ano": 491629.655548393,
        "sellout": 880228.339283104
      }
    ]
  },
  {
    "data": "20200725",
    "lab": "Sandoz",
    "0": [
      {
        "sellin": 0.0,
        "sellout_esse_ano": 642674.045754961,
        "sellout": 1245461.41782022
      }
    ]
  },
  {
    "data": "20200725",
    "lab": "Teva",
    "0": [
      {
        "sellin": 0.0,
        "sellout_esse_ano": 4135532.97287265,
        "sellout": 7275078.34798051
      }
    ]
  },
  {
    "data": "20200725",
    "lab": "Uriach-Theralab",
    "0": [
      {
        "sellin": 9709.6087065254,
        "sellout_esse_ano": 147448.8686457,
        "sellout": 282536.988144736
      }
    ]
  },
  {
    "data": "20200725",
    "lab": "Vemedia Consumer Health",
    "0": [
      {
        "sellin": 20567.5686920665,
        "sellout_esse_ano": 159358.477172992,
        "sellout": 274595.899433378
      }
    ]
  }
]